pnadium/__init__.py
pnadium/anual/__init__.py
pnadium/anual/anual.py
pnadium/trimestral/__init__.py
pnadium/trimestral/trimestral.py
pnadium-0.24.dist-info/licenses/LICENSE
pnadium-0.24.dist-info/METADATA
pnadium-0.24.dist-info/WHEEL
pnadium-0.24.dist-info/top_level.txt
pnadium-0.24.dist-info/RECORD
