Metadata-Version: 2.4
Name: pnadium
Version: 0.24
Summary: Pacote para download e processamento dos microdados da PNAD Contínua do IBGE.
Home-page: https://github.com/ggximenez/pnadium
Author: Gustavo G. Ximenez
Author-email: ggximenez@gmail.com
Classifier: Programming Language :: Python :: 3
Classifier: License :: OSI Approved :: MIT License
Classifier: Operating System :: OS Independent
Requires-Python: >=3.6
License-File: LICENSE
Requires-Dist: pandas
Requires-Dist: numpy
Requires-Dist: unidecode
Requires-Dist: appdirs
Dynamic: author
Dynamic: author-email
Dynamic: classifier
Dynamic: description
Dynamic: description-content-type
Dynamic: home-page
Dynamic: license-file
Dynamic: requires-dist
Dynamic: requires-python
Dynamic: summary
